OmnissiahPrayer/OmnissiahPrayer.py
OmnissiahPrayer/__init__.py
OmnissiahPrayer/holy_words.json
omnissiahprayer-1.0.1.dist-info/licenses/LICENSE
omnissiahprayer-1.0.1.dist-info/METADATA
omnissiahprayer-1.0.1.dist-info/WHEEL
omnissiahprayer-1.0.1.dist-info/top_level.txt
omnissiahprayer-1.0.1.dist-info/RECORD
