Metadata-Version: 2.4
Name: OmnissiahPrayer
Version: 1.0.1
Summary: A ritual Python program that invokes the Machine God.
Home-page: https://github.com/CountZero-Error/OmnissiahPrayer
Author: CountZero
Author-email: zdavidx007@gmail.com
License: MIT
Classifier: Programming Language :: Python :: 3
Classifier: License :: OSI Approved :: MIT License
Classifier: Operating System :: OS Independent
Classifier: Topic :: Religion
Classifier: Topic :: Artistic Software
Classifier: Intended Audience :: Developers
Requires-Python: >=3.7
License-File: LICENSE
Dynamic: author
Dynamic: author-email
Dynamic: classifier
Dynamic: description
Dynamic: description-content-type
Dynamic: home-page
Dynamic: license
Dynamic: license-file
Dynamic: requires-python
Dynamic: summary
